setup.py
distributions_byKNZ/Binomialdistribution.py
distributions_byKNZ/Gaussiandistribution.py
distributions_byKNZ/Generaldistribution.py
distributions_byKNZ/__init__.py
distributions_byKNZ.egg-info/PKG-INFO
distributions_byKNZ.egg-info/SOURCES.txt
distributions_byKNZ.egg-info/dependency_links.txt
distributions_byKNZ.egg-info/not-zip-safe
distributions_byKNZ.egg-info/top_level.txt