Metadata-Version: 1.0
Name: distributions-byKNZ
Version: 0.1
Summary: Gaussian and Binomial distributions
Home-page: UNKNOWN
Author: Kanza Syed
Author-email: UNKNOWN
License: UNKNOWN
Platform: UNKNOWN
